evo_tools/__init__.py
evo_tools/bin_gray.py
evo_tools/custom.py
evo_tools/example.py
evo_tools/helpers.py
evo_tools/population.py
test/__init__.py
test/algorithm.py
test/setup.py
test/test_bin_gray.py
test/test_canonical_algorithm.py
evo_tools-2.3.0.dist-info/LICENSE
evo_tools-2.3.0.dist-info/METADATA
evo_tools-2.3.0.dist-info/WHEEL
evo_tools-2.3.0.dist-info/entry_points.txt
evo_tools-2.3.0.dist-info/top_level.txt
evo_tools-2.3.0.dist-info/RECORD
