Metadata-Version: 2.1
Name: evo-tools
Version: 2.3.0
Summary: Evolutionary programming tools
Author: AnthonyLzq (Anthony Luzquiños)
Author-email: <sluzquinosa@uni.pe>
Project-URL: Source Code, https://gitlab.com/AnthonyLzq/evo_tools
Keywords: python,evolutionary programming
Classifier: Development Status :: 1 - Planning
Classifier: Intended Audience :: Developers
Classifier: Programming Language :: Python :: 3
Classifier: Operating System :: Unix
Classifier: Operating System :: MacOS :: MacOS X
Classifier: Operating System :: Microsoft :: Windows
License-File: LICENSE
Requires-Dist: sympy
Requires-Dist: numpy
Requires-Dist: pandas
